{"neurons":[{"trace":{"elegibility":{},"extended":{}},"state":0,"old":0,"activation":2.5121951219512195,"bias":0,"layer":"input","squash":"LOGISTIC"},{"trace":{"elegibility":{},"extended":{}},"state":0,"old":0,"activation":3.3902439024390243,"bias":0,"layer":"input","squash":"LOGISTIC"},{"trace":{"elegibility":{},"extended":{}},"state":0,"old":0,"activation":0.6341463414634146,"bias":0,"layer":"input","squash":"LOGISTIC"},{"trace":{"elegibility":{},"extended":{}},"state":0,"old":0,"activation":3.6707317073170733,"bias":0,"layer":"input","squash":"LOGISTIC"},{"trace":{"elegibility":{},"extended":{}},"state":0,"old":0,"activation":17.28,"bias":0,"layer":"input","squash":"LOGISTIC"},{"trace":{"elegibility":{},"extended":{}},"state":0,"old":0,"activation":0.8170731707317073,"bias":0,"layer":"input","squash":"LOGISTIC"},{"trace":{"elegibility":{},"extended":{}},"state":0,"old":0,"activation":3.7195121951219514,"bias":0,"layer":"input","squash":"LOGISTIC"},{"trace":{"elegibility":{},"extended":{}},"state":0,"old":0,"activation":78.03,"bias":0,"layer":"input","squash":"LOGISTIC"},{"trace":{"elegibility":{},"extended":{}},"state":0,"old":0,"activation":0.07317073170731707,"bias":0,"layer":"input","squash":"LOGISTIC"},{"trace":{"elegibility":{},"extended":{}},"state":0,"old":0,"activation":0.06097560975609756,"bias":0,"layer":"input","squash":"LOGISTIC"},{"trace":{"elegibility":{},"extended":{}},"state":0,"old":0,"activation":28.304878048780488,"bias":0,"layer":"input","squash":"LOGISTIC"},{"trace":{"elegibility":{},"extended":{}},"state":0,"old":0,"activation":8.9,"bias":0,"layer":"input","squash":"LOGISTIC"},{"trace":{"elegibility":{},"extended":{}},"state":0,"old":0,"activation":33.1219512195122,"bias":0,"layer":"input","squash":"LOGISTIC"},{"trace":{"elegibility":{},"extended":{}},"state":0,"old":0,"activation":0.898,"bias":0,"layer":"input","squash":"LOGISTIC"},{"trace":{"elegibility":{},"extended":{}},"state":-6.889229777100576,"old":-6.792262453518739,"activation":0.0010176614736838725,"bias":0.999997708256267,"layer":"0","squash":"LOGISTIC"},{"trace":{"elegibility":{},"extended":{}},"state":10.078320744602001,"old":9.827635181679133,"activation":0.999958021909207,"bias":1.0000000174868988,"layer":"0","squash":"LOGISTIC"},{"trace":{"elegibility":{},"extended":{}},"state":10.124773895990945,"old":9.495713140784334,"activation":0.9999599272485483,"bias":1.0000062828244747,"layer":"0","squash":"LOGISTIC"},{"trace":{"elegibility":{},"extended":{}},"state":-26.74240094089103,"old":-25.1700084083725,"activation":2.4317719156806655e-12,"bias":0.9999837966358405,"layer":"0","squash":"LOGISTIC"},{"trace":{"elegibility":{},"extended":{}},"state":27.425663560340183,"old":26.495400471480874,"activation":0.9999999999987721,"bias":1.0079131828805026,"layer":"0","squash":"LOGISTIC"},{"trace":{"elegibility":{},"extended":{}},"state":-2.024653361748912,"old":-1.6039485162660865,"activation":0.1166386799748941,"bias":0.9999912139575358,"layer":"0","squash":"LOGISTIC"},{"trace":{"elegibility":{},"extended":{}},"state":4.851918529196783,"old":4.409967042584152,"activation":0.992247202522013,"bias":1.0000393270562782,"layer":"0","squash":"LOGISTIC"},{"trace":{"elegibility":{},"extended":{}},"state":0.8926874212473977,"old":0.22943959863013427,"activation":0.7094444504799743,"bias":1.0000936880402187,"layer":"0","squash":"LOGISTIC"},{"trace":{"elegibility":{},"extended":{}},"state":5.056883894412852,"old":4.952645711285537,"activation":0.993674897790113,"bias":1.0000323948952226,"layer":"1","squash":"LOGISTIC"},{"trace":{"elegibility":{},"extended":{}},"state":5.447035334332243,"old":4.8330875000895785,"activation":0.9957094276396546,"bias":1.0000007035698286,"layer":"1","squash":"LOGISTIC"},{"trace":{"elegibility":{},"extended":{}},"state":-8.966093153417898,"old":-8.78625726139413,"activation":0.00012764969402547925,"bias":0.9999873372375733,"layer":"1","squash":"LOGISTIC"},{"trace":{"elegibility":{},"extended":{}},"state":7.973096398938656,"old":8.643421371252161,"activation":0.9996555084340645,"bias":0.999923699133665,"layer":"1","squash":"LOGISTIC"},{"trace":{"elegibility":{},"extended":{}},"state":-3.817314176778712,"old":-3.270932420643259,"activation":0.021513756151835026,"bias":1.000013034943753,"layer":"1","squash":"LOGISTIC"},{"trace":{"elegibility":{},"extended":{}},"state":5.845984428414862,"old":5.5488630244016255,"activation":0.99711684974171,"bias":0.9999999596675169,"layer":"1","squash":"LOGISTIC"},{"trace":{"elegibility":{},"extended":{}},"state":10.018913469299852,"old":9.481989278191202,"activation":0.9999554526557062,"bias":0.9999999937801815,"layer":"1","squash":"LOGISTIC"},{"trace":{"elegibility":{},"extended":{}},"state":0.3603674829060115,"old":0.539564355295481,"activation":0.5891293883959363,"bias":1.0001111281394675,"layer":"1","squash":"LOGISTIC"},{"trace":{"elegibility":{},"extended":{}},"state":-25.727622131500603,"old":-25.798282213769873,"activation":6.708658358512799e-12,"bias":-0.09267603682374935,"layer":"2","squash":"LOGISTIC"},{"trace":{"elegibility":{},"extended":{}},"state":842.7796832994444,"old":842.3227443315274,"activation":1,"bias":0.026096923714142715,"layer":"2","squash":"LOGISTIC"},{"trace":{"elegibility":{},"extended":{}},"state":-42.67493472973053,"old":-37.447227071142564,"activation":2.9275972551169006e-19,"bias":-0.058147628803008194,"layer":"2","squash":"LOGISTIC"},{"trace":{"elegibility":{},"extended":{}},"state":0.13844236092157772,"old":0.13402231485843416,"activation":0.534555416266329,"bias":0.004466215638542973,"layer":"2","squash":"LOGISTIC"},{"trace":{"elegibility":{},"extended":{}},"state":10.862264531004714,"old":10.803960551648872,"activation":0.9999808322944731,"bias":-0.008858662026569533,"layer":"2","squash":"LOGISTIC"},{"trace":{"elegibility":{},"extended":{}},"state":121.93695001967293,"old":122.11900858910298,"activation":1,"bias":0.09319787591661437,"layer":"2","squash":"LOGISTIC"},{"trace":{"elegibility":{},"extended":{}},"state":-130109.44774136595,"old":-130108.39553197296,"activation":0,"bias":0.02663494051265854,"layer":"2","squash":"LOGISTIC"},{"trace":{"elegibility":{},"extended":{}},"state":-12.191724371146993,"old":-12.289255813629488,"activation":0.000005072232797141275,"bias":-0.009422335685680069,"layer":"2","squash":"LOGISTIC"},{"trace":{"elegibility":{},"extended":{}},"state":5.378823268248868,"old":5.736001850630517,"activation":0.9954079370302262,"bias":1.0000079625821718,"layer":"3","squash":"LOGISTIC"},{"trace":{"elegibility":{},"extended":{}},"state":-31.364308388043305,"old":-29.806860828132113,"activation":2.3914094349763546e-14,"bias":1.0034046018495495,"layer":"3","squash":"LOGISTIC"},{"trace":{"elegibility":{},"extended":{}},"state":-48.54505392603193,"old":-43.69869466871867,"activation":8.263251216519981e-22,"bias":0.99396376973269,"layer":"3","squash":"LOGISTIC"},{"trace":{"elegibility":{},"extended":{}},"state":-28.526442005643933,"old":-24.988816302526327,"activation":4.0843565609174884e-13,"bias":1.0172722663665859,"layer":"3","squash":"LOGISTIC"},{"trace":{"elegibility":{},"extended":{}},"state":-21.057502959105197,"old":-20.218411279878183,"activation":7.158840096252279e-10,"bias":1.0023639168186207,"layer":"3","squash":"LOGISTIC"},{"trace":{"elegibility":{},"extended":{}},"state":-14.914275654940113,"old":-14.244691065331004,"activation":3.3328229004516684e-7,"bias":0.9990546227516672,"layer":"3","squash":"LOGISTIC"},{"trace":{"elegibility":{},"extended":{}},"state":7.79532952784279,"old":7.394409014388098,"activation":0.9995885162779597,"bias":0.9999998387926148,"layer":"3","squash":"LOGISTIC"},{"trace":{"elegibility":{},"extended":{}},"state":-6.029092295489763,"old":-5.807226484762679,"activation":0.0024018954557072842,"bias":0.9999324641591477,"layer":"3","squash":"LOGISTIC"},{"trace":{"elegibility":{},"extended":{}},"state":-4254.764760176618,"old":-3283.3902359339027,"activation":0,"bias":-905.586152958495,"layer":"output","squash":"LOGISTIC"}],"connections":[{"from":"0","to":"30","weight":-0.0004168116537354498,"gater":"14"},{"from":"0","to":"31","weight":-0.007453480857921205,"gater":"15"},{"from":"0","to":"32","weight":-0.049158988221092194,"gater":"16"},{"from":"0","to":"33","weight":-0.054006246985826345,"gater":"17"},{"from":"0","to":"34","weight":0.0374337428348668,"gater":"18"},{"from":"0","to":"35","weight":-0.010628916863329603,"gater":"19"},{"from":"0","to":"36","weight":-0.050340517231295005,"gater":"20"},{"from":"0","to":"37","weight":0.012094474022733606,"gater":"21"},{"from":"0","to":"14","weight":-0.06159509264192475,"gater":null},{"from":"0","to":"15","weight":-0.08098170239872886,"gater":null},{"from":"0","to":"16","weight":-0.03991199628555223,"gater":null},{"from":"0","to":"17","weight":0.04909605001699637,"gater":null},{"from":"0","to":"18","weight":-0.04157135602821687,"gater":null},{"from":"0","to":"19","weight":-0.04561924893925561,"gater":null},{"from":"0","to":"20","weight":0.07221476842885599,"gater":null},{"from":"0","to":"21","weight":0.03398618872699363,"gater":null},{"from":"0","to":"22","weight":0.021084841425596284,"gater":null},{"from":"0","to":"23","weight":-0.06052122419209589,"gater":null},{"from":"0","to":"24","weight":-0.08673334027678264,"gater":null},{"from":"0","to":"25","weight":0.030016705599041474,"gater":null},{"from":"0","to":"26","weight":-0.09749935324033711,"gater":null},{"from":"0","to":"27","weight":-0.0011116217498861533,"gater":null},{"from":"0","to":"28","weight":0.017222476146349208,"gater":null},{"from":"0","to":"29","weight":0.02362399750908691,"gater":null},{"from":"0","to":"38","weight":0.0806980598409332,"gater":null},{"from":"0","to":"39","weight":-0.01906669367957311,"gater":null},{"from":"0","to":"40","weight":-0.0781292619530451,"gater":null},{"from":"0","to":"41","weight":-0.08408701135581889,"gater":null},{"from":"0","to":"42","weight":0.07546694788143317,"gater":null},{"from":"0","to":"43","weight":0.056448722256542225,"gater":null},{"from":"0","to":"44","weight":-0.030873244994442137,"gater":null},{"from":"0","to":"45","weight":0.07358656382312656,"gater":null},{"from":"0","to":"46","weight":2926.9903911903057,"gater":null},{"from":"1","to":"30","weight":-0.042768991847889445,"gater":"14"},{"from":"1","to":"31","weight":-0.0390266695770634,"gater":"15"},{"from":"1","to":"32","weight":0.08056337137716064,"gater":"16"},{"from":"1","to":"33","weight":0.03414451862116817,"gater":"17"},{"from":"1","to":"34","weight":-0.020511748392124732,"gater":"18"},{"from":"1","to":"35","weight":-0.08081985924537582,"gater":"19"},{"from":"1","to":"36","weight":-0.01893432953140267,"gater":"20"},{"from":"1","to":"37","weight":-0.06862100038801626,"gater":"21"},{"from":"1","to":"14","weight":-0.012347522017896862,"gater":null},{"from":"1","to":"15","weight":0.022958619420351052,"gater":null},{"from":"1","to":"16","weight":0.06360089948626117,"gater":null},{"from":"1","to":"17","weight":0.009386436221839834,"gater":null},{"from":"1","to":"18","weight":0.021910592294572814,"gater":null},{"from":"1","to":"19","weight":-0.0897048956505416,"gater":null},{"from":"1","to":"20","weight":0.09536216085864753,"gater":null},{"from":"1","to":"21","weight":-0.062108471763303495,"gater":null},{"from":"1","to":"22","weight":-0.07221601763954433,"gater":null},{"from":"1","to":"23","weight":0.04925060531012245,"gater":null},{"from":"1","to":"24","weight":0.07190936521858354,"gater":null},{"from":"1","to":"25","weight":0.05655597497237091,"gater":null},{"from":"1","to":"26","weight":0.0667775403289382,"gater":null},{"from":"1","to":"27","weight":-0.09553331397618499,"gater":null},{"from":"1","to":"28","weight":0.04481641948305952,"gater":null},{"from":"1","to":"29","weight":-0.08273252301444417,"gater":null},{"from":"1","to":"38","weight":-0.04554603782103389,"gater":null},{"from":"1","to":"39","weight":0.07302703391435403,"gater":null},{"from":"1","to":"40","weight":0.09400491017312447,"gater":null},{"from":"1","to":"41","weight":0.237535667207768,"gater":null},{"from":"1","to":"42","weight":-0.0309752287673215,"gater":null},{"from":"1","to":"43","weight":-0.010720149827799341,"gater":null},{"from":"1","to":"44","weight":-0.04838410702281152,"gater":null},{"from":"1","to":"45","weight":-0.06808462903737393,"gater":null},{"from":"1","to":"46","weight":-3800.518428051095,"gater":null},{"from":"2","to":"30","weight":-0.07290178654580057,"gater":"14"},{"from":"2","to":"31","weight":0.004667781707469895,"gater":"15"},{"from":"2","to":"32","weight":0.017383009314244493,"gater":"16"},{"from":"2","to":"33","weight":-0.040168136827863306,"gater":"17"},{"from":"2","to":"34","weight":-0.060727043462189795,"gater":"18"},{"from":"2","to":"35","weight":0.06556174867344773,"gater":"19"},{"from":"2","to":"36","weight":-0.061513812983663006,"gater":"20"},{"from":"2","to":"37","weight":-0.09833592269897119,"gater":"21"},{"from":"2","to":"14","weight":-0.05665227720733527,"gater":null},{"from":"2","to":"15","weight":0.059741413237769325,"gater":null},{"from":"2","to":"16","weight":0.045958993140793714,"gater":null},{"from":"2","to":"17","weight":-0.06398747818201549,"gater":null},{"from":"2","to":"18","weight":-0.05706091073040405,"gater":null},{"from":"2","to":"19","weight":0.008924519498512931,"gater":null},{"from":"2","to":"20","weight":0.07410339132425535,"gater":null},{"from":"2","to":"21","weight":0.0932131068182282,"gater":null},{"from":"2","to":"22","weight":0.027735316452963486,"gater":null},{"from":"2","to":"23","weight":0.020016460715960128,"gater":null},{"from":"2","to":"24","weight":-0.022808762239431696,"gater":null},{"from":"2","to":"25","weight":-0.052498344370136694,"gater":null},{"from":"2","to":"26","weight":0.0858539485081399,"gater":null},{"from":"2","to":"27","weight":0.02621627827488492,"gater":null},{"from":"2","to":"28","weight":0.00036110575338103526,"gater":null},{"from":"2","to":"29","weight":0.027870927829821007,"gater":null},{"from":"2","to":"38","weight":0.0280475622527251,"gater":null},{"from":"2","to":"39","weight":-0.07276970532442177,"gater":null},{"from":"2","to":"40","weight":-0.019453181745612343,"gater":null},{"from":"2","to":"41","weight":0.025828628448790057,"gater":null},{"from":"2","to":"42","weight":0.05408008679999181,"gater":null},{"from":"2","to":"43","weight":-0.014859368699382904,"gater":null},{"from":"2","to":"44","weight":-0.024808180256630303,"gater":null},{"from":"2","to":"45","weight":-0.014680728026712544,"gater":null},{"from":"2","to":"46","weight":1047.4065166199448,"gater":null},{"from":"3","to":"30","weight":-0.06575836590335657,"gater":"14"},{"from":"3","to":"31","weight":-0.06891617386033697,"gater":"15"},{"from":"3","to":"32","weight":0.028064474353147018,"gater":"16"},{"from":"3","to":"33","weight":-0.018742004464881695,"gater":"17"},{"from":"3","to":"34","weight":0.0692182697983677,"gater":"18"},{"from":"3","to":"35","weight":-0.036086875063074474,"gater":"19"},{"from":"3","to":"36","weight":-0.0810088619165874,"gater":"20"},{"from":"3","to":"37","weight":-0.022334108396787757,"gater":"21"},{"from":"3","to":"14","weight":-0.004532857953994913,"gater":null},{"from":"3","to":"15","weight":0.00875519100220112,"gater":null},{"from":"3","to":"16","weight":-0.0672138689537994,"gater":null},{"from":"3","to":"17","weight":0.03142911572011939,"gater":null},{"from":"3","to":"18","weight":-0.012723913430925157,"gater":null},{"from":"3","to":"19","weight":0.0074889242569053235,"gater":null},{"from":"3","to":"20","weight":-0.07709061995592631,"gater":null},{"from":"3","to":"21","weight":-0.0708943442373187,"gater":null},{"from":"3","to":"22","weight":0.02657687478708282,"gater":null},{"from":"3","to":"23","weight":-0.020030787172684486,"gater":null},{"from":"3","to":"24","weight":-0.03752415839355291,"gater":null},{"from":"3","to":"25","weight":-0.09046670873365464,"gater":null},{"from":"3","to":"26","weight":-0.03424747022814654,"gater":null},{"from":"3","to":"27","weight":-0.02335707915609949,"gater":null},{"from":"3","to":"28","weight":-0.08445577891410179,"gater":null},{"from":"3","to":"29","weight":-0.0447923889186649,"gater":null},{"from":"3","to":"38","weight":-0.020373448565557714,"gater":null},{"from":"3","to":"39","weight":-0.03383883650838761,"gater":null},{"from":"3","to":"40","weight":-0.04812101073149115,"gater":null},{"from":"3","to":"41","weight":0.078205484562638,"gater":null},{"from":"3","to":"42","weight":0.01994907495931811,"gater":null},{"from":"3","to":"43","weight":-0.0382731081724167,"gater":null},{"from":"3","to":"44","weight":-0.0877210522140033,"gater":null},{"from":"3","to":"45","weight":-0.06920278368770315,"gater":null},{"from":"3","to":"46","weight":-253.78144280732806,"gater":null},{"from":"4","to":"30","weight":-0.001575744687772757,"gater":"14"},{"from":"4","to":"31","weight":0.04599158401598706,"gater":"15"},{"from":"4","to":"32","weight":-0.8118173614086877,"gater":"16"},{"from":"4","to":"33","weight":0.07731455148947126,"gater":"17"},{"from":"4","to":"34","weight":0.06768382492862267,"gater":"18"},{"from":"4","to":"35","weight":0.04843253957920072,"gater":"19"},{"from":"4","to":"36","weight":0.020320748303797882,"gater":"20"},{"from":"4","to":"37","weight":-0.047173728798046335,"gater":"21"},{"from":"4","to":"14","weight":0.04728580345107392,"gater":null},{"from":"4","to":"15","weight":0.027597108801417983,"gater":null},{"from":"4","to":"16","weight":0.06024996261980542,"gater":null},{"from":"4","to":"17","weight":-0.045213834022167124,"gater":null},{"from":"4","to":"18","weight":0.013253914388272187,"gater":null},{"from":"4","to":"19","weight":0.06940569679975496,"gater":null},{"from":"4","to":"20","weight":-0.03393807798989799,"gater":null},{"from":"4","to":"21","weight":0.08492512751960035,"gater":null},{"from":"4","to":"22","weight":0.0824557452180108,"gater":null},{"from":"4","to":"23","weight":0.017481837231181907,"gater":null},{"from":"4","to":"24","weight":-0.07838181669049518,"gater":null},{"from":"4","to":"25","weight":-0.13428877768889017,"gater":null},{"from":"4","to":"26","weight":-0.03896023228663045,"gater":null},{"from":"4","to":"27","weight":0.08079137599757151,"gater":null},{"from":"4","to":"28","weight":0.03574355277893014,"gater":null},{"from":"4","to":"29","weight":-0.010049141154273534,"gater":null},{"from":"4","to":"38","weight":-0.030599694884370993,"gater":null},{"from":"4","to":"39","weight":-0.21174542906839944,"gater":null},{"from":"4","to":"40","weight":-0.8087767645664647,"gater":null},{"from":"4","to":"41","weight":-0.08544072262039863,"gater":null},{"from":"4","to":"42","weight":-0.08276976618479252,"gater":null},{"from":"4","to":"43","weight":-0.11207543831785463,"gater":null},{"from":"4","to":"44","weight":-0.06681273792131187,"gater":null},{"from":"4","to":"45","weight":-0.060046692946046594,"gater":null},{"from":"4","to":"46","weight":90.9192329734893,"gater":null},{"from":"5","to":"30","weight":0.0709965437124207,"gater":"14"},{"from":"5","to":"31","weight":-0.08020083535305986,"gater":"15"},{"from":"5","to":"32","weight":-0.054544304873452326,"gater":"16"},{"from":"5","to":"33","weight":-0.016088422545242766,"gater":"17"},{"from":"5","to":"34","weight":0.055525233628658556,"gater":"18"},{"from":"5","to":"35","weight":-0.08293854527061947,"gater":"19"},{"from":"5","to":"36","weight":0.03203844196356782,"gater":"20"},{"from":"5","to":"37","weight":0.04560421178461833,"gater":"21"},{"from":"5","to":"14","weight":0.05099741236796031,"gater":null},{"from":"5","to":"15","weight":0.04282529458471443,"gater":null},{"from":"5","to":"16","weight":0.026990698470040805,"gater":null},{"from":"5","to":"17","weight":-0.03781677968506256,"gater":null},{"from":"5","to":"18","weight":-0.0888989041520819,"gater":null},{"from":"5","to":"19","weight":0.019752909843214823,"gater":null},{"from":"5","to":"20","weight":-0.022211874092598363,"gater":null},{"from":"5","to":"21","weight":-0.03576797109356772,"gater":null},{"from":"5","to":"22","weight":-0.06917351087007657,"gater":null},{"from":"5","to":"23","weight":-0.03856568024549961,"gater":null},{"from":"5","to":"24","weight":-0.07470084334351498,"gater":null},{"from":"5","to":"25","weight":0.04474769312687871,"gater":null},{"from":"5","to":"26","weight":0.0338676232635955,"gater":null},{"from":"5","to":"27","weight":-0.06646852907315147,"gater":null},{"from":"5","to":"28","weight":0.0766545103398956,"gater":null},{"from":"5","to":"29","weight":-0.017656210637624237,"gater":null},{"from":"5","to":"38","weight":0.06474136157695855,"gater":null},{"from":"5","to":"39","weight":0.07016605263826092,"gater":null},{"from":"5","to":"40","weight":-0.11267282390843517,"gater":null},{"from":"5","to":"41","weight":0.014094729523424245,"gater":null},{"from":"5","to":"42","weight":0.06545813095368536,"gater":null},{"from":"5","to":"43","weight":0.060568209019915054,"gater":null},{"from":"5","to":"44","weight":-0.012217516764185442,"gater":null},{"from":"5","to":"45","weight":0.0319782332605811,"gater":null},{"from":"5","to":"46","weight":-2846.229899428109,"gater":null},{"from":"6","to":"30","weight":0.04415182173271705,"gater":"14"},{"from":"6","to":"31","weight":0.031005785869411374,"gater":"15"},{"from":"6","to":"32","weight":-0.009087792188803666,"gater":"16"},{"from":"6","to":"33","weight":-0.06221651065280304,"gater":"17"},{"from":"6","to":"34","weight":-0.09635701356901812,"gater":"18"},{"from":"6","to":"35","weight":-0.08162848606280626,"gater":"19"},{"from":"6","to":"36","weight":-0.09272959607492835,"gater":"20"},{"from":"6","to":"37","weight":0.06130880392919273,"gater":"21"},{"from":"6","to":"14","weight":0.02854327916319297,"gater":null},{"from":"6","to":"15","weight":-0.08536859833766335,"gater":null},{"from":"6","to":"16","weight":-0.0834426132774757,"gater":null},{"from":"6","to":"17","weight":-0.007791255605111361,"gater":null},{"from":"6","to":"18","weight":-0.050270506095469215,"gater":null},{"from":"6","to":"19","weight":-0.04453053673518969,"gater":null},{"from":"6","to":"20","weight":-0.06782790617299267,"gater":null},{"from":"6","to":"21","weight":-0.08981439960378856,"gater":null},{"from":"6","to":"22","weight":0.0805006501116292,"gater":null},{"from":"6","to":"23","weight":0.02723323061378852,"gater":null},{"from":"6","to":"24","weight":-0.07846693552832697,"gater":null},{"from":"6","to":"25","weight":0.04058319147990168,"gater":null},{"from":"6","to":"26","weight":-0.05811349393742076,"gater":null},{"from":"6","to":"27","weight":-0.06989098214715456,"gater":null},{"from":"6","to":"28","weight":-0.08467321032535541,"gater":null},{"from":"6","to":"29","weight":0.03549557704875345,"gater":null},{"from":"6","to":"38","weight":-0.09218522167728072,"gater":null},{"from":"6","to":"39","weight":-0.07398284192891047,"gater":null},{"from":"6","to":"40","weight":0.09578977214251695,"gater":null},{"from":"6","to":"41","weight":0.039849918576767576,"gater":null},{"from":"6","to":"42","weight":-0.011185624889509253,"gater":null},{"from":"6","to":"43","weight":0.060343866366027475,"gater":null},{"from":"6","to":"44","weight":-0.027226784052966628,"gater":null},{"from":"6","to":"45","weight":0.027331495678609777,"gater":null},{"from":"6","to":"46","weight":196.5040923172309,"gater":null},{"from":"7","to":"30","weight":-0.04935875379009291,"gater":"14"},{"from":"7","to":"31","weight":-0.03306815544088594,"gater":"15"},{"from":"7","to":"32","weight":-0.24668937055416515,"gater":"16"},{"from":"7","to":"33","weight":-0.09409375324036826,"gater":"17"},{"from":"7","to":"34","weight":0.1109074905148929,"gater":"18"},{"from":"7","to":"35","weight":0.03393302942715024,"gater":"19"},{"from":"7","to":"36","weight":-0.10851430809615441,"gater":"20"},{"from":"7","to":"37","weight":-0.08513738177266003,"gater":"21"},{"from":"7","to":"14","weight":-0.09416762973615299,"gater":null},{"from":"7","to":"15","weight":0.0738895359150351,"gater":null},{"from":"7","to":"16","weight":0.0682193216821539,"gater":null},{"from":"7","to":"17","weight":-0.3121902093405387,"gater":null},{"from":"7","to":"18","weight":0.25254308037361045,"gater":null},{"from":"7","to":"19","weight":-0.041303292094131715,"gater":null},{"from":"7","to":"20","weight":0.07474757563383277,"gater":null},{"from":"7","to":"21","weight":0.020902984168776784,"gater":null},{"from":"7","to":"22","weight":0.02406282341240766,"gater":null},{"from":"7","to":"23","weight":0.05181307010440277,"gater":null},{"from":"7","to":"24","weight":-0.08429944577526438,"gater":null},{"from":"7","to":"25","weight":0.06177783318363529,"gater":null},{"from":"7","to":"26","weight":-0.09597725607412848,"gater":null},{"from":"7","to":"27","weight":0.005752691922861717,"gater":null},{"from":"7","to":"28","weight":0.049500662768089204,"gater":null},{"from":"7","to":"29","weight":0.023461706488964968,"gater":null},{"from":"7","to":"38","weight":0.038575047831166796,"gater":null},{"from":"7","to":"39","weight":-0.32886653180505054,"gater":null},{"from":"7","to":"40","weight":-0.3702429934653488,"gater":null},{"from":"7","to":"41","weight":-0.480158248475121,"gater":null},{"from":"7","to":"42","weight":-0.21130364514255812,"gater":null},{"from":"7","to":"43","weight":-0.12074803310458243,"gater":null},{"from":"7","to":"44","weight":0.09891963302796139,"gater":null},{"from":"7","to":"45","weight":-0.08029106735593007,"gater":null},{"from":"7","to":"46","weight":-27.552659215051833,"gater":null},{"from":"8","to":"30","weight":-0.034635332677642114,"gater":"14"},{"from":"8","to":"31","weight":-0.007733286468928917,"gater":"15"},{"from":"8","to":"32","weight":-0.12729950390081082,"gater":"16"},{"from":"8","to":"33","weight":0.08614431689724474,"gater":"17"},{"from":"8","to":"34","weight":0.07584250736310562,"gater":"18"},{"from":"8","to":"35","weight":-0.013320745921792887,"gater":"19"},{"from":"8","to":"36","weight":-0.027998198990815702,"gater":"20"},{"from":"8","to":"37","weight":-0.043283460878088195,"gater":"21"},{"from":"8","to":"14","weight":-0.03417442457339844,"gater":null},{"from":"8","to":"15","weight":-0.0747690960430479,"gater":null},{"from":"8","to":"16","weight":-0.005150065699469923,"gater":null},{"from":"8","to":"17","weight":0.02750739699367578,"gater":null},{"from":"8","to":"18","weight":-0.03220442425139817,"gater":null},{"from":"8","to":"19","weight":-0.0034337949767261552,"gater":null},{"from":"8","to":"20","weight":0.07244570900730903,"gater":null},{"from":"8","to":"21","weight":0.06714074681636019,"gater":null},{"from":"8","to":"22","weight":0.07623965395879534,"gater":null},{"from":"8","to":"23","weight":-0.046689032136617355,"gater":null},{"from":"8","to":"24","weight":0.09357944339110087,"gater":null},{"from":"8","to":"25","weight":-0.035328316446460596,"gater":null},{"from":"8","to":"26","weight":-0.08051300930468959,"gater":null},{"from":"8","to":"27","weight":0.042682495344397074,"gater":null},{"from":"8","to":"28","weight":0.059743626415788696,"gater":null},{"from":"8","to":"29","weight":0.07371700202585615,"gater":null},{"from":"8","to":"38","weight":0.04259990619879027,"gater":null},{"from":"8","to":"39","weight":-0.03515338554927229,"gater":null},{"from":"8","to":"40","weight":-0.028225898627369815,"gater":null},{"from":"8","to":"41","weight":-0.07132808987867705,"gater":null},{"from":"8","to":"42","weight":-0.003151574195395108,"gater":null},{"from":"8","to":"43","weight":-0.0770793599567916,"gater":null},{"from":"8","to":"44","weight":-0.06687001926573108,"gater":null},{"from":"8","to":"45","weight":0.038662024451955636,"gater":null},{"from":"8","to":"46","weight":2367.7737498596607,"gater":null},{"from":"9","to":"30","weight":0.07179208947910137,"gater":"14"},{"from":"9","to":"31","weight":0.08124015446227212,"gater":"15"},{"from":"9","to":"32","weight":0.0010528101445157374,"gater":"16"},{"from":"9","to":"33","weight":0.023156659466133562,"gater":"17"},{"from":"9","to":"34","weight":-0.06386142311375231,"gater":"18"},{"from":"9","to":"35","weight":-0.03169360336150632,"gater":"19"},{"from":"9","to":"36","weight":0.039024898616634156,"gater":"20"},{"from":"9","to":"37","weight":-0.05948405093227282,"gater":"21"},{"from":"9","to":"14","weight":0.09262615335535568,"gater":null},{"from":"9","to":"15","weight":-0.04508041788316786,"gater":null},{"from":"9","to":"16","weight":-0.04961725007270093,"gater":null},{"from":"9","to":"17","weight":0.09272411128358858,"gater":null},{"from":"9","to":"18","weight":0.05584039711648691,"gater":null},{"from":"9","to":"19","weight":0.02158506782940971,"gater":null},{"from":"9","to":"20","weight":-0.07811116096571667,"gater":null},{"from":"9","to":"21","weight":-0.04018930401223269,"gater":null},{"from":"9","to":"22","weight":0.07091433738445758,"gater":null},{"from":"9","to":"23","weight":0.06659462226518104,"gater":null},{"from":"9","to":"24","weight":0.008108682096151154,"gater":null},{"from":"9","to":"25","weight":-0.03877075935167275,"gater":null},{"from":"9","to":"26","weight":0.08511881608429592,"gater":null},{"from":"9","to":"27","weight":-0.03090676871082018,"gater":null},{"from":"9","to":"28","weight":0.0760257023386894,"gater":null},{"from":"9","to":"29","weight":0.05692639926023268,"gater":null},{"from":"9","to":"38","weight":0.0582286145124373,"gater":null},{"from":"9","to":"39","weight":-0.022361757590836806,"gater":null},{"from":"9","to":"40","weight":-0.10693638404637279,"gater":null},{"from":"9","to":"41","weight":0.08045631074823041,"gater":null},{"from":"9","to":"42","weight":-0.001331318691724332,"gater":null},{"from":"9","to":"43","weight":-0.012278476106157577,"gater":null},{"from":"9","to":"44","weight":0.004352480347060257,"gater":null},{"from":"9","to":"45","weight":-0.01262059007102315,"gater":null},{"from":"9","to":"46","weight":2427.19079782358,"gater":null},{"from":"10","to":"30","weight":0.031558305178765275,"gater":"14"},{"from":"10","to":"31","weight":0.08856723744704639,"gater":"15"},{"from":"10","to":"32","weight":0.10535529900650056,"gater":"16"},{"from":"10","to":"33","weight":-0.020646871796768478,"gater":"17"},{"from":"10","to":"34","weight":0.06068281699467357,"gater":"18"},{"from":"10","to":"35","weight":0.042944231289307896,"gater":"19"},{"from":"10","to":"36","weight":0.04220873997528744,"gater":"20"},{"from":"10","to":"37","weight":-0.05080361379193043,"gater":"21"},{"from":"10","to":"14","weight":-0.02463671625634669,"gater":null},{"from":"10","to":"15","weight":0.05486013555008664,"gater":null},{"from":"10","to":"16","weight":0.01768349420502454,"gater":null},{"from":"10","to":"17","weight":0.010617718350105717,"gater":null},{"from":"10","to":"18","weight":0.09569010174519763,"gater":null},{"from":"10","to":"19","weight":0.0619614889429454,"gater":null},{"from":"10","to":"20","weight":-0.06148755134955522,"gater":null},{"from":"10","to":"21","weight":-0.08028527011259047,"gater":null},{"from":"10","to":"22","weight":0.042002370792809315,"gater":null},{"from":"10","to":"23","weight":-0.05210153508783943,"gater":null},{"from":"10","to":"24","weight":-0.07243714551663809,"gater":null},{"from":"10","to":"25","weight":0.12591505016613702,"gater":null},{"from":"10","to":"26","weight":0.06579990316517664,"gater":null},{"from":"10","to":"27","weight":0.05031413801819468,"gater":null},{"from":"10","to":"28","weight":0.0378857198740329,"gater":null},{"from":"10","to":"29","weight":0.0037931351135380106,"gater":null},{"from":"10","to":"38","weight":0.0825425756190029,"gater":null},{"from":"10","to":"39","weight":-0.07818038752171665,"gater":null},{"from":"10","to":"40","weight":0.0374330930651521,"gater":null},{"from":"10","to":"41","weight":0.3535591326969683,"gater":null},{"from":"10","to":"42","weight":-0.08576051065321967,"gater":null},{"from":"10","to":"43","weight":-0.08390939057885304,"gater":null},{"from":"10","to":"44","weight":-0.02676129399523056,"gater":null},{"from":"10","to":"45","weight":-0.028466658383520173,"gater":null},{"from":"10","to":"46","weight":182.53910747660615,"gater":null},{"from":"11","to":"30","weight":0.05790272861111353,"gater":"14"},{"from":"11","to":"31","weight":0.04479034823808729,"gater":"15"},{"from":"11","to":"32","weight":-0.11239622576920523,"gater":"16"},{"from":"11","to":"33","weight":-0.0595024714335596,"gater":"17"},{"from":"11","to":"34","weight":0.036955264679014034,"gater":"18"},{"from":"11","to":"35","weight":-0.06729629402659615,"gater":"19"},{"from":"11","to":"36","weight":0.04826424381237106,"gater":"20"},{"from":"11","to":"37","weight":0.021156730333446602,"gater":"21"},{"from":"11","to":"14","weight":0.07808816525046706,"gater":null},{"from":"11","to":"15","weight":-0.06706507022574146,"gater":null},{"from":"11","to":"16","weight":-0.04069142691023957,"gater":null},{"from":"11","to":"17","weight":-0.05177692277663315,"gater":null},{"from":"11","to":"18","weight":-0.018397636131926822,"gater":null},{"from":"11","to":"19","weight":-0.0024985674706701298,"gater":null},{"from":"11","to":"20","weight":-0.028772561840803696,"gater":null},{"from":"11","to":"21","weight":-0.026082642249860708,"gater":null},{"from":"11","to":"22","weight":-0.011915170777313392,"gater":null},{"from":"11","to":"23","weight":-0.028522017589594925,"gater":null},{"from":"11","to":"24","weight":0.022116961960143195,"gater":null},{"from":"11","to":"25","weight":-0.045242252098864226,"gater":null},{"from":"11","to":"26","weight":-0.010571484079750318,"gater":null},{"from":"11","to":"27","weight":0.058063824044416915,"gater":null},{"from":"11","to":"28","weight":0.08583176178269233,"gater":null},{"from":"11","to":"29","weight":0.07303321052327676,"gater":null},{"from":"11","to":"38","weight":0.046055592912479626,"gater":null},{"from":"11","to":"39","weight":0.05029821952940861,"gater":null},{"from":"11","to":"40","weight":-0.02850427147961994,"gater":null},{"from":"11","to":"41","weight":0.02281812499936952,"gater":null},{"from":"11","to":"42","weight":-0.12034107889630301,"gater":null},{"from":"11","to":"43","weight":-0.039069485488651454,"gater":null},{"from":"11","to":"44","weight":0.08529761190476907,"gater":null},{"from":"11","to":"45","weight":0.07117593462184266,"gater":null},{"from":"11","to":"46","weight":248.40565398382503,"gater":null},{"from":"12","to":"30","weight":0.08780418674074437,"gater":"14"},{"from":"12","to":"31","weight":0.09746325524740039,"gater":"15"},{"from":"12","to":"32","weight":-0.3438632332061786,"gater":"16"},{"from":"12","to":"33","weight":0.0004823013325736852,"gater":"17"},{"from":"12","to":"34","weight":-0.03259606766078207,"gater":"18"},{"from":"12","to":"35","weight":-0.08002328685955955,"gater":"19"},{"from":"12","to":"36","weight":0.013007644044374909,"gater":"20"},{"from":"12","to":"37","weight":0.053815816861667434,"gater":"21"},{"from":"12","to":"14","weight":-0.03421742339391184,"gater":null},{"from":"12","to":"15","weight":0.0654465980293608,"gater":null},{"from":"12","to":"16","weight":0.09050168503991876,"gater":null},{"from":"12","to":"17","weight":-0.07699380323638506,"gater":null},{"from":"12","to":"18","weight":0.13745378171774073,"gater":null},{"from":"12","to":"19","weight":-0.06471530512879163,"gater":null},{"from":"12","to":"20","weight":0.012819958689323254,"gater":null},{"from":"12","to":"21","weight":0.00017785872324381751,"gater":null},{"from":"12","to":"22","weight":-0.0194325034096103,"gater":null},{"from":"12","to":"23","weight":0.048624665416799634,"gater":null},{"from":"12","to":"24","weight":0.0058988538550415115,"gater":null},{"from":"12","to":"25","weight":0.037002656865232256,"gater":null},{"from":"12","to":"26","weight":0.054870907597123285,"gater":null},{"from":"12","to":"27","weight":0.0552425030454991,"gater":null},{"from":"12","to":"28","weight":0.09733618275186691,"gater":null},{"from":"12","to":"29","weight":-0.08506328870728733,"gater":null},{"from":"12","to":"38","weight":-0.014816471336212306,"gater":null},{"from":"12","to":"39","weight":-0.03598857679445734,"gater":null},{"from":"12","to":"40","weight":-0.23336182964566304,"gater":null},{"from":"12","to":"41","weight":-0.0553736344228893,"gater":null},{"from":"12","to":"42","weight":-0.024272509573977107,"gater":null},{"from":"12","to":"43","weight":-0.0641807192289126,"gater":null},{"from":"12","to":"44","weight":0.02654586728129021,"gater":null},{"from":"12","to":"45","weight":0.016769824717867005,"gater":null},{"from":"12","to":"46","weight":-67.60356534211752,"gater":null},{"from":"13","to":"30","weight":-0.08015565672716284,"gater":"14"},{"from":"13","to":"31","weight":0.04877837344272091,"gater":"15"},{"from":"13","to":"32","weight":-0.11660809490018724,"gater":"16"},{"from":"13","to":"33","weight":-0.07062291851994688,"gater":"17"},{"from":"13","to":"34","weight":-0.08972187345065001,"gater":"18"},{"from":"13","to":"35","weight":-0.02915724826144649,"gater":"19"},{"from":"13","to":"36","weight":-0.02448786123115725,"gater":"20"},{"from":"13","to":"37","weight":0.052608091638061294,"gater":"21"},{"from":"13","to":"14","weight":0.07409251241378169,"gater":null},{"from":"13","to":"15","weight":0.034468365768583795,"gater":null},{"from":"13","to":"16","weight":-0.020158107980842808,"gater":null},{"from":"13","to":"17","weight":0.05128729381018097,"gater":null},{"from":"13","to":"18","weight":-0.05644356837998885,"gater":null},{"from":"13","to":"19","weight":-0.05356415461178414,"gater":null},{"from":"13","to":"20","weight":0.019225820493347097,"gater":null},{"from":"13","to":"21","weight":-0.006038353550779898,"gater":null},{"from":"13","to":"22","weight":-0.02398599594553517,"gater":null},{"from":"13","to":"23","weight":-0.08071061494859864,"gater":null},{"from":"13","to":"24","weight":0.06736135920454434,"gater":null},{"from":"13","to":"25","weight":-0.08837533153167763,"gater":null},{"from":"13","to":"26","weight":0.021881111598631223,"gater":null},{"from":"13","to":"27","weight":0.022660983035046853,"gater":null},{"from":"13","to":"28","weight":0.08074155864335004,"gater":null},{"from":"13","to":"29","weight":0.08354917477608734,"gater":null},{"from":"13","to":"38","weight":-0.08832338053762899,"gater":null},{"from":"13","to":"39","weight":0.043717417153955884,"gater":null},{"from":"13","to":"40","weight":-0.02220073358956811,"gater":null},{"from":"13","to":"41","weight":-0.08884734262774353,"gater":null},{"from":"13","to":"42","weight":-0.05900331789201466,"gater":null},{"from":"13","to":"43","weight":-0.0586916619011409,"gater":null},{"from":"13","to":"44","weight":-0.0016305759474147335,"gater":null},{"from":"13","to":"45","weight":0.07560847250067725,"gater":null},{"from":"13","to":"46","weight":-931.4352908412358,"gater":null},{"from":"30","to":"46","weight":0.017586329582851504,"gater":"38"},{"from":"30","to":"14","weight":-0.09076245304556343,"gater":null},{"from":"30","to":"15","weight":-0.09801872909006301,"gater":null},{"from":"30","to":"16","weight":0.01259763171091186,"gater":null},{"from":"30","to":"17","weight":-0.01881385700337037,"gater":null},{"from":"30","to":"18","weight":0.08856881782412529,"gater":null},{"from":"30","to":"19","weight":0.0054692255578506115,"gater":null},{"from":"30","to":"20","weight":0.008463181316620428,"gater":null},{"from":"30","to":"21","weight":-0.0916711188848985,"gater":null},{"from":"30","to":"22","weight":0.02528598281365492,"gater":null},{"from":"30","to":"23","weight":-0.09693135266585652,"gater":null},{"from":"30","to":"24","weight":0.03277997368194244,"gater":null},{"from":"30","to":"25","weight":-0.09503593171540775,"gater":null},{"from":"30","to":"26","weight":0.0042420964948762475,"gater":null},{"from":"30","to":"27","weight":-0.01639503731976029,"gater":null},{"from":"30","to":"28","weight":0.08905956032701333,"gater":null},{"from":"30","to":"29","weight":0.0648518786387236,"gater":null},{"from":"30","to":"38","weight":-0.06244948120302527,"gater":null},{"from":"30","to":"39","weight":0.03284635144699683,"gater":null},{"from":"30","to":"40","weight":0.051699856301351606,"gater":null},{"from":"30","to":"41","weight":0.08446383844173448,"gater":null},{"from":"30","to":"42","weight":-0.025978664799426288,"gater":null},{"from":"30","to":"43","weight":-0.06074836317077988,"gater":null},{"from":"30","to":"44","weight":-0.026311420611966573,"gater":null},{"from":"30","to":"45","weight":-0.09917507553763324,"gater":null},{"from":"30","to":"30","weight":1,"gater":"22"},{"from":"31","to":"46","weight":-0.04693875880701249,"gater":"39"},{"from":"31","to":"14","weight":-0.05684230871905094,"gater":null},{"from":"31","to":"15","weight":0.040292767876040206,"gater":null},{"from":"31","to":"16","weight":-0.016904507825486623,"gater":null},{"from":"31","to":"17","weight":-0.0926481845485464,"gater":null},{"from":"31","to":"18","weight":-0.09534593694977361,"gater":null},{"from":"31","to":"19","weight":0.013144090930453229,"gater":null},{"from":"31","to":"20","weight":-0.0037782463443120622,"gater":null},{"from":"31","to":"21","weight":-0.04245399695308409,"gater":null},{"from":"31","to":"22","weight":-0.0050654852273716786,"gater":null},{"from":"31","to":"23","weight":0.0513656984698129,"gater":null},{"from":"31","to":"24","weight":0.02145468226386912,"gater":null},{"from":"31","to":"25","weight":-0.025194434931320068,"gater":null},{"from":"31","to":"26","weight":0.07677139478882798,"gater":null},{"from":"31","to":"27","weight":0.08402593576396301,"gater":null},{"from":"31","to":"28","weight":-0.09778682016739847,"gater":null},{"from":"31","to":"29","weight":0.042707458013253916,"gater":null},{"from":"31","to":"38","weight":-0.023476702384250068,"gater":null},{"from":"31","to":"39","weight":0.022576566417288647,"gater":null},{"from":"31","to":"40","weight":-0.023162733635313112,"gater":null},{"from":"31","to":"41","weight":-0.07731883669471294,"gater":null},{"from":"31","to":"42","weight":-0.07475254789263203,"gater":null},{"from":"31","to":"43","weight":-0.021969836329443913,"gater":null},{"from":"31","to":"44","weight":-0.0019658428330220465,"gater":null},{"from":"31","to":"45","weight":0.031699839203103417,"gater":null},{"from":"31","to":"31","weight":1,"gater":"23"},{"from":"32","to":"46","weight":-0.2514643126496458,"gater":"40"},{"from":"32","to":"14","weight":0.09264636847751517,"gater":null},{"from":"32","to":"15","weight":-0.09010678435116666,"gater":null},{"from":"32","to":"16","weight":0.08317092525181478,"gater":null},{"from":"32","to":"17","weight":0.04706011346558055,"gater":null},{"from":"32","to":"18","weight":-0.016067687794567274,"gater":null},{"from":"32","to":"19","weight":-0.010925772730358156,"gater":null},{"from":"32","to":"20","weight":-0.004917149359979952,"gater":null},{"from":"32","to":"21","weight":0.027144739313431008,"gater":null},{"from":"32","to":"22","weight":-0.03675370466324664,"gater":null},{"from":"32","to":"23","weight":0.08435991731447844,"gater":null},{"from":"32","to":"24","weight":-0.07649583604968845,"gater":null},{"from":"32","to":"25","weight":-0.0956667699128763,"gater":null},{"from":"32","to":"26","weight":0.09010181425145465,"gater":null},{"from":"32","to":"27","weight":0.005976457226671775,"gater":null},{"from":"32","to":"28","weight":0.08771118191095426,"gater":null},{"from":"32","to":"29","weight":-0.049227342407436786,"gater":null},{"from":"32","to":"38","weight":0.06337669360157448,"gater":null},{"from":"32","to":"39","weight":0.019639449371577744,"gater":null},{"from":"32","to":"40","weight":-0.00598270389053976,"gater":null},{"from":"32","to":"41","weight":-0.05328386762692932,"gater":null},{"from":"32","to":"42","weight":0.09051782291280501,"gater":null},{"from":"32","to":"43","weight":-0.013265587674765475,"gater":null},{"from":"32","to":"44","weight":0.022374000871835494,"gater":null},{"from":"32","to":"45","weight":0.0988861442455373,"gater":null},{"from":"32","to":"32","weight":1,"gater":"24"},{"from":"33","to":"46","weight":-0.17959116930025784,"gater":"41"},{"from":"33","to":"14","weight":0.0622551669423736,"gater":null},{"from":"33","to":"15","weight":-0.04690572720840539,"gater":null},{"from":"33","to":"16","weight":-0.01686669583420655,"gater":null},{"from":"33","to":"17","weight":0.0013817357598672059,"gater":null},{"from":"33","to":"18","weight":0.053633380587470185,"gater":null},{"from":"33","to":"19","weight":-0.09450285713259128,"gater":null},{"from":"33","to":"20","weight":0.09406425297365946,"gater":null},{"from":"33","to":"21","weight":0.026486900714883244,"gater":null},{"from":"33","to":"22","weight":0.04237023021176931,"gater":null},{"from":"33","to":"23","weight":0.05597917509090565,"gater":null},{"from":"33","to":"24","weight":0.029603424435689744,"gater":null},{"from":"33","to":"25","weight":0.06836222522600864,"gater":null},{"from":"33","to":"26","weight":-0.07340822816313917,"gater":null},{"from":"33","to":"27","weight":-0.03672666040904031,"gater":null},{"from":"33","to":"28","weight":-0.09681429741890255,"gater":null},{"from":"33","to":"29","weight":-0.09323412986613937,"gater":null},{"from":"33","to":"38","weight":-0.03975662054573468,"gater":null},{"from":"33","to":"39","weight":-0.032866587528047095,"gater":null},{"from":"33","to":"40","weight":-0.05116992165880089,"gater":null},{"from":"33","to":"41","weight":0.06890302363756685,"gater":null},{"from":"33","to":"42","weight":0.06454419642868085,"gater":null},{"from":"33","to":"43","weight":0.08165473040899753,"gater":null},{"from":"33","to":"44","weight":0.07541969769811369,"gater":null},{"from":"33","to":"45","weight":-0.061731644069180115,"gater":null},{"from":"33","to":"33","weight":1,"gater":"25"},{"from":"34","to":"46","weight":0.07916984544141112,"gater":"42"},{"from":"34","to":"14","weight":-0.08115165181571883,"gater":null},{"from":"34","to":"15","weight":-0.04198622997092747,"gater":null},{"from":"34","to":"16","weight":0.041068012392362546,"gater":null},{"from":"34","to":"17","weight":-0.039673229133215616,"gater":null},{"from":"34","to":"18","weight":-0.09685140047356386,"gater":null},{"from":"34","to":"19","weight":0.04626341816060614,"gater":null},{"from":"34","to":"20","weight":0.05247522624132439,"gater":null},{"from":"34","to":"21","weight":0.06420579416878537,"gater":null},{"from":"34","to":"22","weight":0.06108460738355014,"gater":null},{"from":"34","to":"23","weight":0.09056682187048319,"gater":null},{"from":"34","to":"24","weight":0.01257121683727997,"gater":null},{"from":"34","to":"25","weight":0.013072808733805884,"gater":null},{"from":"34","to":"26","weight":0.0651708053679692,"gater":null},{"from":"34","to":"27","weight":-0.048603179949088124,"gater":null},{"from":"34","to":"28","weight":-0.008958935690821679,"gater":null},{"from":"34","to":"29","weight":-0.033695942136849275,"gater":null},{"from":"34","to":"38","weight":-0.03555626685855972,"gater":null},{"from":"34","to":"39","weight":-0.003951948799685815,"gater":null},{"from":"34","to":"40","weight":0.04205692664245756,"gater":null},{"from":"34","to":"41","weight":0.016075292430866365,"gater":null},{"from":"34","to":"42","weight":0.032810954167596953,"gater":null},{"from":"34","to":"43","weight":0.006212496189446506,"gater":null},{"from":"34","to":"44","weight":-0.03318443890773778,"gater":null},{"from":"34","to":"45","weight":0.007209087262888263,"gater":null},{"from":"34","to":"34","weight":1,"gater":"26"},{"from":"35","to":"46","weight":0.017023131048466138,"gater":"43"},{"from":"35","to":"14","weight":-0.08629519989962192,"gater":null},{"from":"35","to":"15","weight":0.05429637168846702,"gater":null},{"from":"35","to":"16","weight":0.02140196308828831,"gater":null},{"from":"35","to":"17","weight":0.017367079034576616,"gater":null},{"from":"35","to":"18","weight":-0.028824328679068537,"gater":null},{"from":"35","to":"19","weight":-0.016046267547593557,"gater":null},{"from":"35","to":"20","weight":0.0626529294018925,"gater":null},{"from":"35","to":"21","weight":-0.050585733571208984,"gater":null},{"from":"35","to":"22","weight":0.08203841688641898,"gater":null},{"from":"35","to":"23","weight":0.09616564237233392,"gater":null},{"from":"35","to":"24","weight":-0.014104503749613324,"gater":null},{"from":"35","to":"25","weight":0.05688069764392836,"gater":null},{"from":"35","to":"26","weight":-0.08422589905635024,"gater":null},{"from":"35","to":"27","weight":-0.09697938186449558,"gater":null},{"from":"35","to":"28","weight":-0.07771980916129566,"gater":null},{"from":"35","to":"29","weight":-0.029595007415696744,"gater":null},{"from":"35","to":"38","weight":0.09366437779962614,"gater":null},{"from":"35","to":"39","weight":0.06209878082426762,"gater":null},{"from":"35","to":"40","weight":0.08955762170075214,"gater":null},{"from":"35","to":"41","weight":0.07026234544747666,"gater":null},{"from":"35","to":"42","weight":0.017608805401372468,"gater":null},{"from":"35","to":"43","weight":0.09556771809149273,"gater":null},{"from":"35","to":"44","weight":0.04173489175670427,"gater":null},{"from":"35","to":"45","weight":-0.003835462293635993,"gater":null},{"from":"35","to":"35","weight":1,"gater":"27"},{"from":"36","to":"46","weight":-0.027445467009790652,"gater":"44"},{"from":"36","to":"14","weight":0.019090598180878496,"gater":null},{"from":"36","to":"15","weight":0.08362667717374805,"gater":null},{"from":"36","to":"16","weight":0.078307923441752,"gater":null},{"from":"36","to":"17","weight":-0.009373237133747428,"gater":null},{"from":"36","to":"18","weight":0.08287489027716219,"gater":null},{"from":"36","to":"19","weight":-0.06522982160512619,"gater":null},{"from":"36","to":"20","weight":0.08457896826683269,"gater":null},{"from":"36","to":"21","weight":0.022343288646217034,"gater":null},{"from":"36","to":"22","weight":-0.04079323538685108,"gater":null},{"from":"36","to":"23","weight":-0.030750434761880212,"gater":null},{"from":"36","to":"24","weight":0.04756977907381948,"gater":null},{"from":"36","to":"25","weight":-0.03443471837913646,"gater":null},{"from":"36","to":"26","weight":0.05888446564513923,"gater":null},{"from":"36","to":"27","weight":-0.009447768507555769,"gater":null},{"from":"36","to":"28","weight":-0.008093919046174338,"gater":null},{"from":"36","to":"29","weight":-0.05161979528428893,"gater":null},{"from":"36","to":"38","weight":-0.014651320078032427,"gater":null},{"from":"36","to":"39","weight":-0.03985753780821886,"gater":null},{"from":"36","to":"40","weight":-0.06458522410834429,"gater":null},{"from":"36","to":"41","weight":0.005657442406421003,"gater":null},{"from":"36","to":"42","weight":0.052883068607771276,"gater":null},{"from":"36","to":"43","weight":-0.02903174188582478,"gater":null},{"from":"36","to":"44","weight":0.051398800607780404,"gater":null},{"from":"36","to":"45","weight":0.020147483391232957,"gater":null},{"from":"36","to":"36","weight":1,"gater":"28"},{"from":"37","to":"46","weight":0.06905373994494975,"gater":"45"},{"from":"37","to":"14","weight":0.0306024470889326,"gater":null},{"from":"37","to":"15","weight":0.0512186506160556,"gater":null},{"from":"37","to":"16","weight":-0.009815873753693843,"gater":null},{"from":"37","to":"17","weight":-0.06807239685490066,"gater":null},{"from":"37","to":"18","weight":0.0779257152229547,"gater":null},{"from":"37","to":"19","weight":0.07101750370499539,"gater":null},{"from":"37","to":"20","weight":-0.006317902747345081,"gater":null},{"from":"37","to":"21","weight":-0.005982456235684433,"gater":null},{"from":"37","to":"22","weight":0.007969166755376046,"gater":null},{"from":"37","to":"23","weight":-0.021132474103111358,"gater":null},{"from":"37","to":"24","weight":0.09408861554286095,"gater":null},{"from":"37","to":"25","weight":-0.058231993529314616,"gater":null},{"from":"37","to":"26","weight":0.05584446767870584,"gater":null},{"from":"37","to":"27","weight":-0.019092041100510094,"gater":null},{"from":"37","to":"28","weight":0.06275514285081217,"gater":null},{"from":"37","to":"29","weight":-0.035816253962671483,"gater":null},{"from":"37","to":"38","weight":-0.050250336762447514,"gater":null},{"from":"37","to":"39","weight":-0.07887483772714023,"gater":null},{"from":"37","to":"40","weight":0.07942670558185436,"gater":null},{"from":"37","to":"41","weight":0.014578777664830057,"gater":null},{"from":"37","to":"42","weight":-0.07998094342408152,"gater":null},{"from":"37","to":"43","weight":-0.07614787391058249,"gater":null},{"from":"37","to":"44","weight":-0.03320354399765662,"gater":null},{"from":"37","to":"45","weight":-0.0008049870623606526,"gater":null},{"from":"37","to":"37","weight":1,"gater":"29"}]}